ksd_metric/kernel/__init__.py
ksd_metric/kernel/kernel.py
ksd_metric/stein/__init__.py
ksd_metric/stein/stein.py
ksd_metric/target/__init__.py
ksd_metric/target/target.py
ksd_metric/typing/__init__.py
ksd_metric/typing/typing.py
ksd_metric/utils/__init__.py
ksd_metric/utils/utils.py
ksd_metric-0.2.0.dist-info/licenses/LICENSE
ksd_metric-0.2.0.dist-info/METADATA
ksd_metric-0.2.0.dist-info/WHEEL
ksd_metric-0.2.0.dist-info/top_level.txt
ksd_metric-0.2.0.dist-info/RECORD
