Metadata-Version: 2.4
Name: ksd-metric
Version: 0.2.0
Summary: Kernel Stein Discrepancy
Requires-Python: >=3.10
License-File: LICENSE
Requires-Dist: jax>=0.4.13
Requires-Dist: jaxlib>=0.4.13
Requires-Dist: jaxtyping>=0.2.19
Requires-Dist: sphinx>=8.1.3
Requires-Dist: sphinx-autobuild>=2024.10.3
Requires-Dist: sphinx-autodoc-typehints>=3.0.1
Requires-Dist: sphinx-rtd-theme>=3.0.2
Provides-Extra: docs
Requires-Dist: sphinx; extra == "docs"
Requires-Dist: sphinx_rtd_theme; extra == "docs"
Requires-Dist: sphinx-autodoc-typehints; extra == "docs"
Requires-Dist: sphinx-markdown-builder; extra == "docs"
Dynamic: license-file
